LICENSE
MANIFEST.in
README.md
qrimg.py
requirements.txt
setup.py
qrimg.egg-info/PKG-INFO
qrimg.egg-info/SOURCES.txt
qrimg.egg-info/dependency_links.txt
qrimg.egg-info/entry_points.txt
qrimg.egg-info/requires.txt
qrimg.egg-info/top_level.txt