Metadata-Version: 2.1
Name: qrimg
Version: 0.2.0
Summary: Generate QRCode Image
Home-page: https://github.com/zencore-cn/zencore-issues
Author: zencore
Author-email: appstore@zencore.cn
License: MIT
Keywords: qrimg
Platform: UNKNOWN
Classifier: Development Status :: 5 - Production/Stable
Classifier: Intended Audience :: Developers
Classifier: Topic :: Software Development :: Libraries :: Python Modules
Classifier: License :: OSI Approved :: MIT License
Classifier: Programming Language :: Python :: 3
Classifier: Programming Language :: Python :: 3 :: Only
